{
  "name": "Chase Turner",
  "age": 43,
  "address": {
    "street": "Awemok Manor",
    "city": "Iflejab",
    "state": "NC",
    "zip": "27997"
  },
  "contact": {
    "phone": "(407) 402-4170",
    "servicePhone": "800992419"
  },
  "birthday": "1995-05-16T20:24:49.230Z",
  "ip": "101.50.240.197",
  "foo": "bar",
  "profile": {
    "about": "Fa sawode nacovpo waaze mejsa ijucigic zizagvo kubbucci ohonese efokifuf badlawo te vurkedad aseragkoz ugeda zisopose ifo vefsinoz. Var dunolida ki zasucul luvaoz acvaroze unu gun jofgud ce kiri ibaesa godub. Jobdat ge su doov ulafu fevesof huno ekunaga fef kowe utze delar lahjuj vi wun bo. Jim zi ogova mi ofiso upetul wubbem puiz rene cun tu pigcu mijifvup bep. Bel asfovzo moulfi dorad dab vovjatid ziba tij vovzaheg nutboptu hawod rapevsu nifvinuv. Nuziz zubunca ki wim feh ka biezocu tatbujap kamugtin zes ragnohhe law cosi. Niuw bajippi vonih su fovivzo wu la jagnatah rul cawah pitnikho tazwid kiz ad kav.",
    "bio": "Cehhebu ji tefmog caberune puztiov uzhuf tiwtamvu ni apu ifijugmi peknenpup sedrolhov sa kiejo norozfoj. Tu eg now vuddaor vop guhul ibisurfaw jabag luk secih elwobu obge hubo vu ajbugzu. Ec ibila zaheni pozfu wit guruc icahu tus aznuce ka dacorsom ihibimdum faci tic tonod zefnob. Hif refegov rokhuiv asseswu vuh vuvo nakotoje al elodagu nabtuk jala win jekom zit luz ke je. Es irgig cedawoh jah iwugageg mej hodubiso ref awijav ofadiw witpag lepoz. Guifoza gowalip em lupif mis eh ogiga alikoseho mahkalati ti idurura cabuno icewuuse zarotbu. Fi ro kut guj ururuil imueti raal gesa mewafif af wemovel rata rut labritlo fomuv hoh opa."
  },
  "apiKey": "0659c5c8b25918c42755b62fb6e2de625caf0c757d0b64252b37b214ee19a52e",
  "currency": {
    "code": "HNL",
    "name": "Honduras Lempira"
  }
}