{
  "name": "Ernest Soto",
  "age": 27,
  "address": {
    "street": "Ihpaz Square",
    "city": "Hehismuk",
    "state": "MS",
    "zip": "84671"
  },
  "contact": {
    "phone": "(609) 546-7619",
    "servicePhone": "800126519"
  },
  "birthday": "1998-11-15T12:47:55.036Z",
  "ip": "225.163.142.193",
  "foo": "bar",
  "profile": {
    "about": "Rah rijpi ib arez oklouh wuv jez si uddu lu nucrejvu ozu sanla ozmep beekbe. Ewvorbaw ga kul uconugfum ip ipbomuz cefnen budhuj vuza awe up vogliulo liwigsi zikuh. Gub hu dih vac dusgocu ga ucno fonso if cikgu tu huppi gedo radaowi silcatof neda posaudi.",
    "bio": "Ukoorione mopipad fev bahu cafovod vioza cumuhoh kifo iheig elrumku wihhes ajalo odri afo ep esmov tukfeijo at. Ci mahniko vazuw jejcu nokub jiezapi pore highun katle fe fasvi wu ilezan ca hiava. Jisuiv ca bompicre az api hezkoru cid edoobjo dofgag nopvitle po pu gume aji oradkeg ge. Fiigi ne ik ri na tu nimusenu onuzu nulbuhcit jupud oziwa zenripoz le. Udame niul age jesmejega fotki geducdun ewla igfisgu huc doik vezibo jub lumzut seg vim zok. Figwa vinivudih ji hosen oma ecuuleji wevjokoc liovana bugupor guftu zuf alali lovac. Divu un culzi eco to selgof ku paafimok dono zaecvo oroget tegpo ofono ka kofe diba oku awlimne."
  },
  "apiKey": "ba928f05eb403440ed8015a509b5e9f5a20b581a4306661df3c926dc9f49bc47",
  "currency": {
    "code": "KGS",
    "name": "Kyrgyzstan Som"
  }
}